torrent_stream
