Metadata-Version: 1.1
Name: django-torrent-stream
Version: 0.9.3
Summary: Wraps the Torrent Stream http://torrentstream.org/
Home-page: http://github.com/adw0rd/django-torrent-stream
Author: Mikhail Andreev
Author-email: x11org@gmail.com
License: BSD
Keywords: django,torrent,torrent stream
Platform: UNKNOWN
Classifier: Development Status :: 3 - Alpha
Classifier: Environment :: Web Environment
Classifier: Programming Language :: Python
Classifier: Framework :: Django
Classifier: License :: OSI Approved :: BSD License
Classifier: Topic :: Software Development :: Libraries :: Application Frameworks
Classifier: Topic :: Software Development :: Libraries :: Python Modules
